src/__init__.py
src/uniqcharstest/__init__.py
src/uniqcharstest/main.py
src/uniqcharstest/app/__init__.py
src/uniqcharstest/app/app.py
src/uniqcharstest/utils/__init__.py
src/uniqcharstest/utils/exceptions.py
src/uniqcharstest/utils/functions.py
tests/__init__.py
uniqcharstest-1.0.dist-info/LICENSE
uniqcharstest-1.0.dist-info/METADATA
uniqcharstest-1.0.dist-info/WHEEL
uniqcharstest-1.0.dist-info/entry_points.txt
uniqcharstest-1.0.dist-info/top_level.txt
uniqcharstest-1.0.dist-info/RECORD
